MANIFEST.in
README.md
setup.py
gmailresthandler/__init__.py
gmailresthandler/authentication.py
gmailresthandler/config.py
gmailresthandler/exceptions.py
gmailresthandler/handler.py
gmailresthandler.egg-info/PKG-INFO
gmailresthandler.egg-info/SOURCES.txt
gmailresthandler.egg-info/dependency_links.txt
gmailresthandler.egg-info/not-zip-safe
gmailresthandler.egg-info/requires.txt
gmailresthandler.egg-info/top_level.txt