Metadata-Version: 1.0
Name: gmailresthandler
Version: 0.60
Summary: Helper classes for working with Gmail API client.
Home-page: https://github.com/joelcolucci/gmailresthandler
Author: Joel Colucci
Author-email: joelcolucci@gmail.com
License: MIT
Platform: UNKNOWN
